sane_finances/__init__.py
sane_finances/annotations.py
sane_finances/retry_policy.py
sane_finances/communication/__init__.py
sane_finances/communication/cachers.py
sane_finances/communication/downloader.py
sane_finances/communication/url_downloader.py
sane_finances/inspection/__init__.py
sane_finances/inspection/analyzers.py
sane_finances/inspection/serialize.py
sane_finances/sources/__init__.py
sane_finances/sources/base.py
sane_finances/sources/computing.py
sane_finances/sources/generic.py
sane_finances/sources/inspection.py
sane_finances/sources/bloomberg/__init__.py
sane_finances/sources/bloomberg/v2021/__init__.py
sane_finances/sources/bloomberg/v2021/exporters.py
sane_finances/sources/bloomberg/v2021/meta.py
sane_finances/sources/bloomberg/v2021/parsers.py
sane_finances/sources/cbr/__init__.py
sane_finances/sources/cbr/v2016/__init__.py
sane_finances/sources/cbr/v2016/exporters.py
sane_finances/sources/cbr/v2016/meta.py
sane_finances/sources/cbr/v2016/parsers.py
sane_finances/sources/ishares/__init__.py
sane_finances/sources/ishares/v2021/__init__.py
sane_finances/sources/ishares/v2021/exporters.py
sane_finances/sources/ishares/v2021/meta.py
sane_finances/sources/ishares/v2021/parsers.py
sane_finances/sources/lbma/__init__.py
sane_finances/sources/lbma/v2021/__init__.py
sane_finances/sources/lbma/v2021/exporters.py
sane_finances/sources/lbma/v2021/meta.py
sane_finances/sources/lbma/v2021/parsers.py
sane_finances/sources/moex/__init__.py
sane_finances/sources/moex/v1_3/__init__.py
sane_finances/sources/moex/v1_3/exporters.py
sane_finances/sources/moex/v1_3/meta.py
sane_finances/sources/moex/v1_3/parsers.py
sane_finances/sources/msci/__init__.py
sane_finances/sources/msci/v1/__init__.py
sane_finances/sources/msci/v1/exporters.py
sane_finances/sources/msci/v1/meta.py
sane_finances/sources/msci/v1/parsers.py
sane_finances/sources/msci/v2021/__init__.py
sane_finances/sources/msci/v2021/exporters.py
sane_finances/sources/msci/v2021/meta.py
sane_finances-2.1.dist-info/LICENSE
sane_finances-2.1.dist-info/METADATA
sane_finances-2.1.dist-info/WHEEL
sane_finances-2.1.dist-info/top_level.txt
sane_finances-2.1.dist-info/RECORD
