Metadata-Version: 2.1
Name: sane-finances
Version: 2.1
Summary: A library for download and parse financial data from different sources
Home-page: https://github.com/StanleySane/sane-finances
Author: Sane Development
Author-email: sane.development.org@gmail.com
License: BSD 3-Clause License
Project-URL: Bug Tracker, https://github.com/StanleySane/sane-finances/issues
Project-URL: Source, https://github.com/StanleySane/sane-finances
Keywords: MSCI,MOEX,Moscow Exchange,Solactive,CBR,Bank of Russia,Yahoo Finance,S&P,Dow Jones,iShares,LBMA,Bloomberg,Stocks,Bonds,ETF
Classifier: Programming Language :: Python :: 3
Classifier: Programming Language :: Python :: 3 :: Only
Classifier: Programming Language :: Python :: 3.8
Classifier: Programming Language :: Python :: 3.9
Classifier: License :: OSI Approved :: BSD License
Classifier: Operating System :: OS Independent
Classifier: Topic :: Software Development :: Libraries :: Python Modules
Classifier: Development Status :: 5 - Production/Stable
Classifier: Intended Audience :: Education
Classifier: Intended Audience :: Financial and Insurance Industry
Classifier: Intended Audience :: Information Technology
Requires-Python: >=3.8
License-File: LICENSE
